Metadata-Version: 1.1
Name: django-mailman-eso
Version: 0.4.1
Summary: Interface to Mailman Web-API
Home-page: https://github.com/JuanCerquera/django-mailman-eso
Author: Bernd Schlapsi
Author-email: albert@albertoconnor.ca
License: GNU LGPL v2.1
Download-URL: https://github.com/JuanCerquera/django-mailman-eso/archive/refs/tags/0.4.1.tar.gz
Platform: any
